flowise/__init__.py
flowise/client.py
flowise-1.0.4.dist-info/LICENSE.md
flowise-1.0.4.dist-info/METADATA
flowise-1.0.4.dist-info/WHEEL
flowise-1.0.4.dist-info/top_level.txt
flowise-1.0.4.dist-info/RECORD
