Metadata-Version: 2.1
Name: flowise
Version: 1.0.4
Summary: Flowise SDK for Python to interact with the Flowise API.
Home-page: https://github.com/FlowiseAI/FlowisePy
Author: Henry Heng
Author-email: support@flowiseai.com
Classifier: Programming Language :: Python :: 3
Classifier: License :: OSI Approved :: MIT License
Classifier: Operating System :: OS Independent
Requires-Python: >=3.7
License-File: LICENSE.md
